Module_hello_word/__init__.py
Module_hello_word/One_son_Module/__init__.py
Module_hello_word/One_son_Module/Two_son_Module/__init__.py
Module_hello_word/One_son_Module/Two_son_Module/Three_son_Module/__init__.py
Module_hello_word/One_son_Module/Two_son_Module/Three_son_Module/hello.py
Module_hello_word/One_son_Module/Two_son_Module/Three_son_Module/lql.py
hello_world_zhaobudao-1.0.1.dist-info/METADATA
hello_world_zhaobudao-1.0.1.dist-info/WHEEL
hello_world_zhaobudao-1.0.1.dist-info/top_level.txt
hello_world_zhaobudao-1.0.1.dist-info/RECORD
