Metadata-Version: 2.1
Name: hello-world-zhaobudao
Version: 1.0.1
Summary: 你好，世界！！
Home-page: http://www.XXXXX.com
Author: lql
License: UNKNOWN
Platform: UNKNOWN
